{
  "current": {
    "color_account_bg": "#000000",
    "color_account_text": "#ffffff",
    "color_header_bg": "#000000",
    "color_header_text": "#ffffff",
    "color_body_bg": "#ffffff",
    "color_body_text": "#000000",
    "color_primary": "#d9b073",
    "color_splash": "#d9b073",
    "color_border": "#b2b2b2",
    "homepage_background_light": "#f7f7f7",
    "homepage_background_dark": "#2e3830",
    "product_background_color": "#ffffff",
    "color_footer_bg": "#000000",
    "color_footer_text": "#ffffff",
    "color_footer_social_link": "#ffffff",
    "font_title": "google:sansStack:Montserrat:400",
    "font_title_capitalize": true,
    "font_body": "google:sansStack:Open+Sans:400",
    "font_accent": "google:sansStack:Montserrat:400",
    "logo_use_image": true,
    "header_padding": "30px",
    "main_menu_linklist": "main-menu",
    "meganav_use_image": false,
    "meganav_link": "",
    "header_enable_search": false,
    "search_only_products": false,
    "favicon_enable": false,
    "footer_logo_enable": "none",
    "footer_mainlinks": "footer",
    "footer_content": "",
    "footer_newsletter_enable": true,
    "footer_newsletter_text": "Subscribe to get special offers, free giveaways, and once-in-a-lifetime deals.",
    "newsletter_form_action": "",
    "footer_secondary_linklist": "",
    "home_section_1": "home-collection",
    "home_section_2": "home-hero",
    "home_section_3": "home-collection",
    "home_section_4": "home-custom-section",
    "home_section_5": "home-blog",
    "home_section_6": "home-instagram",
    "home_section_7": "",
    "homepage_hero_height": "80px",
    "hero_overlay_opacity": "0.2",
    "hero_headline": "",
    "hero_description": "<br>\r\n<br>\r\n<br>\r\n<br>",
    "homepage_hero_align": "text-center",
    "hero_link_text": "",
    "hero_link": "",
    "homepage_hero_cta_image_enable": false,
    "home_enable_video": false,
    "homepage_video_vimeo_url": "https:\/\/vimeo.com\/171159234",
    "home_collection": "",
    "homepage_collection_color": "homepage--white",
    "homepage_collection_subtitle": "Featured Products",
    "home_page_content": "frontpage",
    "homepage_page_color": "homepage--white",
    "home_product": "send-it-unisex",
    "homepage_product_subtitle": "Buy Now",
    "homepage_product_color": "homepage--light",
    "homepage_lower_link_text": "GET LOST WITH US",
    "homepage_lower_link": "http:\/\/www.turn-loose.com\/pages\/about-us",
    "homepage_blog": "news",
    "homepage_blog_subtitle": "Adventure Stories",
    "homepage_blog_color": "homepage--white",
    "homepage_instagram_subtitle": "FOLLOW @turn.loose",
    "homepage_instagram_color": "homepage--white",
    "instagram_id": "2333759365.b534787.ef39e1aa5303472dac8c67292b7b87a5",
    "description_position": "auto",
    "product_breadcrumbs": true,
    "product_quantity": true,
    "product_nav_enable": true,
    "product_show_vendor": false,
    "related_products_enable": false,
    "global_grid_width_large": "large--one-half",
    "global_grid_width_medium": "medium--one-half",
    "global_grid_width_small": "small--one-half",
    "collection_text_alignment": "center",
    "product_grid_style": "under",
    "collection_custom_nav_list": "",
    "collection_standard_nav": false,
    "collection_type_nav": false,
    "collection_vendor_nav": false,
    "collection_tag_nav": false,
    "collection_sorting": true,
    "collection_image_height": "160px",
    "collection_overlay_opacity": "0.2",
    "blog_sidebar_enable": false,
    "blog_show_tags": true,
    "blog_twitter_enable": false,
    "blog_twitter_widget": "",
    "cart_type": "modal",
    "cart_notes_enable": false,
    "cart_vendor_enable": false,
    "twittercard_handle": "",
    "social_twitter_link": "",
    "social_facebook_link": "https:\/\/www.facebook.com\/laurengregg55\/?fref=ts",
    "social_instagram_link": "https:\/\/www.instagram.com\/turn.loose\/",
    "social_pinterest_link": "",
    "social_youtube_link": "",
    "social_vimeo_link": "",
    "social_tumblr_link": "",
    "social_fancy_link": "",
    "footer_social_enable": true,
    "product_social_enable": false,
    "blog_social_enable": false,
    "share_enable_facebook": true,
    "share_enable_twitter": false,
    "share_enable_pinterest": true,
    "share_enable_google": true,
    "checkout_header_image": "shopify:\/\/shop_images\/checkout_header_image_4.jpg",
    "checkout_use_storefront_logo": false,
    "checkout_logo_image": "shopify:\/\/shop_images\/checkout_logo_4.png",
    "checkout_logo_position": "left",
    "checkout_logo_size": "medium",
    "checkout_body_background_image": "",
    "checkout_body_background_color": "#675857",
    "checkout_input_background_color_mode": "transparent",
    "checkout_sidebar_background_image": "",
    "checkout_sidebar_background_color": "#f7f7f7",
    "checkout_heading_font": "Lato",
    "checkout_body_font": "Open Sans",
    "checkout_accent_color": "#fccdb9",
    "checkout_button_color": "#78bf73",
    "checkout_error_color": "#b93e5c",
    "checkout_use_header_image": true,
    "checkout_logo": "checkout_logo.png",
    "checkout_use_body_background_image": false,
    "checkout_use_sidebar_background_image": false,
    "checkout_banner_background_color": "#ffffff",
    "checkout_headline": "",
    "checkout_call_to_action_color": "#1391a4",
    "color_header_border": "#000000",
    "display_theme_credit": true,
    "blog_enable_facebook": true,
    "blog_enable_pinterest": true,
    "blog_enable_google": true,
    "blog_enable_twitter": true,
    "homepage_page_columns_enable": true,
    "home_section_8": "home-instagram",
    "homepage_logosection_subtitle": "As Seen In",
    "homepage_logosection_color": "homepage--splash",
    "homepage_logosection_1_enable": false,
    "homepage_logosection_1_link": "http:\/\/shopify.com",
    "homepage_logosection_2_enable": false,
    "homepage_logosection_2_link": "http:\/\/shopify.com",
    "homepage_logosection_3_enable": true,
    "homepage_logosection_3_link": "http:\/\/shopify.com",
    "homepage_logosection_4_enable": true,
    "homepage_logosection_4_link": "http:\/\/shopify.com",
    "homepage_logosection_5_enable": true,
    "homepage_logosection_5_link": "http:\/\/shopify.com",
    "homepage_logosection_6_enable": true,
    "homepage_logosection_6_link": "http:\/\/shopify.com",
    "home_page_columns_enable": true,
    "homepage_page_subtitle": "I am the walrus",
    "homepage_page_title_enable": false,
    "homepage_page_hr_enable": false,
    "blog_hide_tags": true,
    "products_grid_width": "medium--one-half large--one-quarter",
    "home_enable_hero": true,
    "social_rss_enable": false,
    "content_for_index": []
  },
  "presets": {
    "Pipeline": {
      "color_account_bg": "#000000",
      "color_account_text": "#ffffff",
      "color_header_bg": "#ffffff",
      "color_header_text": "#000000",
      "color_body_bg": "#ffffff",
      "color_body_text": "#000000",
      "color_primary": "#000000",
      "color_splash": "#1391a4",
      "color_border": "#bebebe",
      "homepage_background_light": "#f7f7f7",
      "homepage_background_dark": "#2e3438",
      "product_background_color": "#f7f7f7",
      "color_footer_bg": "#f7f7f7",
      "color_footer_text": "#000000",
      "color_footer_social_link": "#111010",
      "font_title": "google:sansStack:Oswald:400",
      "font_title_capitalize": true,
      "font_body": "google:serifStack:PT+Serif:400",
      "font_accent": "google:sansStack:Montserrat:400",
      "logo_use_image": false,
      "header_padding": "30px",
      "main_menu_linklist": "main-menu",
      "meganav_use_image": false,
      "header_enable_search": true,
      "search_only_products": false,
      "favicon_enable": false,
      "footer_logo_enable": "none",
      "footer_mainlinks": "main-menu",
      "footer_newsletter_enable": true,
      "footer_newsletter_text": "Subscribe to get special offers, free giveaways, and once-in-a-lifetime deals.",
      "footer_secondary_linklist": "footer",
      "home_section_1": "home-hero",
      "home_section_2": "home-page",
      "home_section_3": "home-collection",
      "home_section_4": "home-custom-section",
      "home_section_5": "home-blog",
      "home_section_6": "home-instagram",
      "home_section_7": "",
      "homepage_hero_height": "300px",
      "hero_overlay_opacity": "0.15",
      "hero_description": "Edit this text in your theme settings",
      "homepage_hero_align": "text-center",
      "homepage_hero_cta_image_enable": false,
      "home_enable_video": false,
      "homepage_collection_color": "homepage--white",
      "homepage_page_color": "homepage--white",
      "homepage_product_color": "homepage--light",
      "homepage_blog_color": "homepage--white",
      "homepage_instagram_color": "homepage--white",
      "description_position": "auto",
      "product_breadcrumbs": true,
      "product_quantity": true,
      "product_nav_enable": true,
      "product_show_vendor": false,
      "related_products_enable": true,
      "global_grid_width_large": "large--one-third",
      "global_grid_width_medium": "medium--one-third",
      "global_grid_width_small": "small--one-half",
      "collection_text_alignment": "center",
      "product_grid_style": "hover",
      "collection_custom_nav_list": "",
      "collection_standard_nav": false,
      "collection_type_nav": false,
      "collection_vendor_nav": false,
      "collection_tag_nav": false,
      "collection_sorting": false,
      "collection_image_height": "160px",
      "collection_overlay_opacity": "0.1",
      "blog_sidebar_enable": false,
      "blog_show_tags": true,
      "blog_twitter_enable": false,
      "cart_type": "modal",
      "cart_notes_enable": false,
      "cart_vendor_enable": false,
      "footer_social_enable": true,
      "product_social_enable": false,
      "blog_social_enable": false,
      "share_enable_facebook": false,
      "share_enable_twitter": false,
      "share_enable_pinterest": false,
      "share_enable_google": false,
      "checkout_use_header_image": false,
      "checkout_banner_background_color": "#ffffff",
      "checkout_logo": "",
      "checkout_accent_color": "#1391a4",
      "checkout_button_color": "#1391a4",
      "checkout_call_to_action_color": "#1391a4",
      "color_header_border": "#03141d",
      "display_theme_credit": true,
      "blog_enable_facebook": true,
      "blog_enable_pinterest": true,
      "blog_enable_google": true,
      "blog_enable_twitter": true,
      "homepage_page_columns_enable": true,
      "checkout_logo_position": "left",
      "checkout_logo_size": "medium",
      "checkout_use_body_background_image": false,
      "checkout_body_background_color": "#ffffff",
      "checkout_input_background_color_mode": "white",
      "checkout_use_sidebar_background_image": false,
      "checkout_sidebar_background_color": "#f7f7f7",
      "checkout_heading_font": "Oswald",
      "checkout_body_font": "PT Serif",
      "checkout_error_color": "#1391a4"
    },
    "Play": {
      "color_account_bg": "#000000",
      "color_account_text": "#ffffff",
      "color_header_bg": "#000000",
      "color_header_text": "#ffffff",
      "color_body_bg": "#ffffff",
      "color_body_text": "#000000",
      "color_primary": "#78bf73",
      "color_splash": "#78bf73",
      "color_border": "#b2b2b2",
      "homepage_background_light": "#f7f7f7",
      "homepage_background_dark": "#2e3830",
      "product_background_color": "#ffffff",
      "color_footer_bg": "#000000",
      "color_footer_text": "#ffffff",
      "color_footer_social_link": "#ffffff",
      "font_title": "google:sansStack:Montserrat:400",
      "font_title_capitalize": true,
      "font_body": "google:sansStack:Open+Sans:400",
      "font_accent": "google:sansStack:Montserrat:400",
      "logo_use_image": false,
      "header_padding": "20px",
      "main_menu_linklist": "main-menu",
      "meganav_use_image": false,
      "header_enable_search": false,
      "search_only_products": false,
      "favicon_enable": false,
      "footer_logo_enable": "none",
      "footer_mainlinks": "footer",
      "footer_newsletter_enable": true,
      "footer_newsletter_text": "Subscribe to get special offers, free giveaways, and once-in-a-lifetime deals.",
      "footer_secondary_linklist": "",
      "home_section_1": "home-hero",
      "home_section_2": "home-collection",
      "home_section_3": "home-custom-section",
      "home_section_4": "home-product",
      "home_section_5": "home-blog",
      "home_section_6": "home-instagram",
      "home_section_7": "",
      "homepage_hero_height": "260px",
      "hero_overlay_opacity": "0.2",
      "hero_description": "Edit this section in your theme settings",
      "homepage_hero_align": "text-center",
      "homepage_hero_cta_image_enable": false,
      "home_enable_video": false,
      "homepage_collection_color": "homepage--white",
      "homepage_page_color": "homepage--white",
      "homepage_product_color": "homepage--light",
      "homepage_blog_color": "homepage--white",
      "homepage_instagram_color": "homepage--white",
      "description_position": "auto",
      "product_breadcrumbs": true,
      "product_quantity": true,
      "product_nav_enable": true,
      "product_show_vendor": false,
      "related_products_enable": false,
      "global_grid_width_large": "large--one-half",
      "global_grid_width_medium": "medium--one-half",
      "global_grid_width_small": "small--one-half",
      "collection_text_alignment": "center",
      "product_grid_style": "under",
      "collection_custom_nav_list": "",
      "collection_standard_nav": false,
      "collection_type_nav": false,
      "collection_vendor_nav": false,
      "collection_tag_nav": false,
      "collection_sorting": true,
      "collection_image_height": "160px",
      "collection_overlay_opacity": "0.2",
      "blog_sidebar_enable": true,
      "blog_show_tags": true,
      "blog_twitter_enable": false,
      "cart_type": "modal",
      "cart_notes_enable": false,
      "cart_vendor_enable": false,
      "footer_social_enable": true,
      "product_social_enable": false,
      "blog_social_enable": false,
      "share_enable_facebook": true,
      "share_enable_twitter": false,
      "share_enable_pinterest": true,
      "share_enable_google": true,
      "checkout_use_header_image": false,
      "checkout_banner_background_color": "#ffffff",
      "checkout_logo": "",
      "checkout_accent_color": "#78bf73",
      "checkout_button_color": "#78bf73",
      "checkout_call_to_action_color": "#1391a4",
      "color_header_border": "#000000",
      "display_theme_credit": true,
      "blog_enable_facebook": true,
      "blog_enable_pinterest": true,
      "blog_enable_google": true,
      "blog_enable_twitter": true,
      "homepage_page_columns_enable": true,
      "checkout_logo_position": "left",
      "checkout_logo_size": "medium",
      "checkout_use_body_background_image": false,
      "checkout_body_background_color": "#ffffff",
      "checkout_input_background_color_mode": "white",
      "checkout_use_sidebar_background_image": false,
      "checkout_sidebar_background_color": "#f7f7f7",
      "checkout_heading_font": "Lato",
      "checkout_body_font": "Open Sans",
      "checkout_error_color": "#b93e5c"
    }
  }
}